src/7z2hashcat.pl
src/7z2john.pl
src/__init__.py
src/attackers.py
src/bashutil.py
src/tt7zcrack.py
tt7zcrack-0.2.0.dist-info/LICENSE
tt7zcrack-0.2.0.dist-info/METADATA
tt7zcrack-0.2.0.dist-info/WHEEL
tt7zcrack-0.2.0.dist-info/entry_points.txt
tt7zcrack-0.2.0.dist-info/top_level.txt
tt7zcrack-0.2.0.dist-info/RECORD
