Metadata-Version: 2.1
Name: tt7zcrack
Version: 0.2.0
Summary: Fast 7zip crack assistant tool which support GPU/CPU.
Home-page: https://github.com/tp7309/tt7zcrack
Author: tp7309
Author-email: yiyou7309@gmail.com
License: Apache License Version 2.0
Keywords: 7z 7zip password crack hashcat jtr john gpu
Classifier: Programming Language :: Python :: 3
Requires-Python: >=3.5
License-File: LICENSE
